kendama/__init__.py
kendama/api_client.py
kendama/api_response.py
kendama/configuration.py
kendama/exceptions.py
kendama/py.typed
kendama/rest.py
kendama/api/__init__.py
kendama/api/v1_api.py
kendama/models/__init__.py
kendama/models/announcement.py
kendama/models/response_body.py
openapi_client/__init__.py
openapi_client/api_client.py
openapi_client/api_response.py
openapi_client/configuration.py
openapi_client/exceptions.py
openapi_client/rest.py
openapi_client/api/__init__.py
openapi_client/api/v1_api.py
openapi_client/models/__init__.py
openapi_client/models/announcement.py
openapi_client/models/response_body.py
kendama-0.1.3.dist-info/LICENSE.txt
kendama-0.1.3.dist-info/METADATA
kendama-0.1.3.dist-info/WHEEL
kendama-0.1.3.dist-info/top_level.txt
kendama-0.1.3.dist-info/RECORD
