Metadata-Version: 2.1
Name: kendama
Version: 0.1.3
Summary: 国税庁API
Home-page: https://github.com/uichi/kendama-python
Author: uichi
Author-email: 37263474+uichi@users.noreply.github.com
License: MIT
Project-URL: Documentation, https://github.com/uichi/kendama-python/blob/main/README.md
Project-URL: Source, https://github.com/uichi/kendama-python
Keywords: OpenAPI,OpenAPI-Generator,国税庁API
Platform: UNKNOWN
License-File: LICENSE.txt
Requires-Dist: urllib3 (<2.1.0,>=1.25.3)
Requires-Dist: python-dateutil
Requires-Dist: pydantic (<2,>=1.10.5)
Requires-Dist: aenum
